{"GlobalPropertiesHash":"3OxcAO45XzKZVdMbONglJGSxabNmZdJoguIs5pl3Pco=","FingerprintPatternsHash":"gq3WsqcKBUGTSNle7RKKyXRIwh7M8ccEqOqYvIzoM04=","PropertyOverridesHash":"8ZRc1sGeVrPBx4lD717BgRaQekyh78QKV9SKsdt638U=","InputHashes":["Tqv0/1SMsgG0BEpe21OqTmWH0\u002B5p8Qd77XG/C5bIC7k=","QaKwRcGkWyR4De3\u002BcP/a6SG2Dp/7QuQXK0iQbC29x4o="],"CachedAssets":{"QaKwRcGkWyR4De3\u002BcP/a6SG2Dp/7QuQXK0iQbC29x4o=":{"Identity":"C:\\Users\\Pedro\\Documents\\IzziProjectsAIP\\IzziAutomationAIP\\WebApp\\wwwroot\\index.html","SourceId":"IzziWebApp","SourceType":"Discovered","ContentRoot":"C:\\Users\\Pedro\\Documents\\IzziProjectsAIP\\IzziAutomationAIP\\WebApp\\wwwroot\\","BasePath":"_content/IzziWebApp","RelativePath":"index#[.{fingerprint}]?.html","AssetKind":"All","AssetMode":"All","AssetRole":"Primary","AssetMergeBehavior":null,"AssetMergeSource":"","RelatedAsset":null,"AssetTraitName":null,"AssetTraitValue":null,"Fingerprint":"fba1qnj72a","Integrity":"hQ\u002BkhcO0OSPljFBgsG4Nhd6sLZTXymAwcrZ4RCI6FVQ=","CopyToOutputDirectory":"Never","CopyToPublishDirectory":"PreserveNewest","OriginalItemSpec":"wwwroot\\index.html","FileLength":8874,"LastWriteTime":"2026-03-01T19:38:18.9223865+00:00"},"Tqv0/1SMsgG0BEpe21OqTmWH0\u002B5p8Qd77XG/C5bIC7k=":{"Identity":"C:\\Users\\Pedro\\Documents\\IzziProjectsAIP\\IzziAutomationAIP\\WebApp\\wwwroot\\app.js","SourceId":"IzziWebApp","SourceType":"Discovered","ContentRoot":"C:\\Users\\Pedro\\Documents\\IzziProjectsAIP\\IzziAutomationAIP\\WebApp\\wwwroot\\","BasePath":"_content/IzziWebApp","RelativePath":"app#[.{fingerprint}]?.js","AssetKind":"All","AssetMode":"All","AssetRole":"Primary","AssetMergeBehavior":null,"AssetMergeSource":"","RelatedAsset":null,"AssetTraitName":null,"AssetTraitValue":null,"Fingerprint":"6r31nnfs95","Integrity":"QuwgYJO80\u002BhbucCkLKmCb3WxGfBEBDkNxb/Tplu2Aoc=","CopyToOutputDirectory":"Never","CopyToPublishDirectory":"PreserveNewest","OriginalItemSpec":"wwwroot\\app.js","FileLength":14287,"LastWriteTime":"2026-03-01T20:14:35.9621014+00:00"}},"CachedCopyCandidates":{}}